npgsm/__init__.py
npgsm/core/__init__.py
npgsm/core/tools.py
npgsm-2024.8.20.dist-info/LICENSE
npgsm-2024.8.20.dist-info/METADATA
npgsm-2024.8.20.dist-info/WHEEL
npgsm-2024.8.20.dist-info/top_level.txt
npgsm-2024.8.20.dist-info/RECORD
